{
    "keep": {
        "days": true,
        "amount": 14
    },
    "auditLog": "log\\.6425b6ef59d56488746d0ccea1d2ee6caecd0fd0-audit.json",
    "files": [
        {
            "date": 1575058842317,
            "name": "log\\error-2019-11-29-14.log",
            "hash": "829d3b64a78f4e42d32c3bc89be7fa5a"
        },
        {
            "date": 1575062379643,
            "name": "log\\error-2019-11-29-15.log",
            "hash": "cafb58c2f2fbce1bd2df39c49b788259"
        },
        {
            "date": 1575248782819,
            "name": "log\\error-2019-12-01-19.log",
            "hash": "c3cdfbf0f7ae352b867ef139f72d8b71"
        },
        {
            "date": 1575335720488,
            "name": "log\\error-2019-12-02-19.log",
            "hash": "ba812ba985c3189f9b602d51879c74fe"
        },
        {
            "date": 1575342895649,
            "name": "log\\error-2019-12-02-21.log",
            "hash": "219d299acffacbf6165a4316dabcf061"
        },
        {
            "date": 1575433710139,
            "name": "log\\error-2019-12-03-22.log",
            "hash": "1e93ee80ccaa4c32330cc97eb709efb0"
        }
    ]
}